missinglink_cli.py
missinglink/__init__.py
missinglink/commands/__init__.py
missinglink/commands/as_api.py
missinglink/commands/auth.py
missinglink/commands/aws.py
missinglink/commands/azure.py
missinglink/commands/code_command.py
missinglink/commands/commons.py
missinglink/commands/data.py
missinglink/commands/defaults.py
missinglink/commands/experiments.py
missinglink/commands/gcp.py
missinglink/commands/global_cli.py
missinglink/commands/http_session.py
missinglink/commands/install.py
missinglink/commands/install_command.py
missinglink/commands/logs_handlers.py
missinglink/commands/mali_version.py
missinglink/commands/ml_sentry.py
missinglink/commands/models.py
missinglink/commands/orgs.py
missinglink/commands/projects.py
missinglink/commands/resources.py
missinglink/commands/run.py
missinglink/commands/sse_firebase.py
missinglink/commands/utils.py
missinglink/commands/cloud/__init__.py
missinglink/commands/cloud/backend_context.py
missinglink/commands/cloud/cloud_connector.py
missinglink/commands/cloud/aws/__init__.py
missinglink/commands/cloud/aws/aws_context.py
missinglink/commands/cloud/aws/base_aws.py
missinglink/commands/cloud/aws/cloud_formation.py
missinglink/commands/cloud/aws/iam.py
missinglink/commands/cloud/aws/sts.py
missinglink/commands/cloud/aws/wrappers.py
missinglink/commands/cloud/azure/__init__.py
missinglink/commands/cloud/azure/azure_context.py
missinglink/commands/cloud/gcp/__init__.py
missinglink/commands/cloud/gcp/custom_roles.py
missinglink/commands/cloud/gcp/deployment_resources.jinja2
missinglink/commands/cloud/gcp/gcp-requirements.txt
missinglink/commands/cloud/gcp/gcp_context.py
missinglink/commands/cloud/gcp/gcp_utils.py
missinglink/commands/utilities/__init__.py
missinglink/commands/utilities/aws_auth.py
missinglink/commands/utilities/aws_policy.json
missinglink/commands/utilities/aws_sts_assume_policy.json
missinglink/commands/utilities/click_utils.py
missinglink/commands/utilities/cloud_credentials_handler.py
missinglink-19.10.26630.dist-info/METADATA
missinglink-19.10.26630.dist-info/WHEEL
missinglink-19.10.26630.dist-info/entry_points.txt
missinglink-19.10.26630.dist-info/top_level.txt
missinglink-19.10.26630.dist-info/RECORD
