Metadata-Version: 2.1
Name: missinglink
Version: 19.10.26630
Summary: Command line tool and SDK for MissingLink.ai platform
Home-page: https://missinglink.ai
Author: missinglink.ai
Author-email: support@missinglink.ai
License: Apache
Platform: UNKNOWN
Classifier: Development Status :: 4 - Beta
Classifier: Intended Audience :: Developers
Classifier: License :: OSI Approved :: Apache Software License
Classifier: Programming Language :: Python
Classifier: Programming Language :: Python :: 2.7
Classifier: Programming Language :: Python :: 3.4
Classifier: Programming Language :: Python :: 3.5
Classifier: Programming Language :: Python :: 3.5
Classifier: Programming Language :: Python :: 3.6
Classifier: Programming Language :: Python :: 3.6
Classifier: Programming Language :: Python :: 3.7
Requires-Dist: Click (~=7.0)
Requires-Dist: requests (~=2.20)
Requires-Dist: terminaltables (~=3.1)
Requires-Dist: PyJWT (~=1.6)
Requires-Dist: humanize (~=0.5)
Requires-Dist: tqdm (~=4.28)
Requires-Dist: Flask (~=1.0)
Requires-Dist: httplib2 (~=0.12)
Requires-Dist: GitPython (~=2.1)
Requires-Dist: boto3 (~=1.9)
Requires-Dist: click-completion (~=0.5)
Requires-Dist: pandas (~=0.23)
Requires-Dist: PyYAML (~=5.0)
Requires-Dist: docker (~=3.5)
Requires-Dist: colorama (~=0.3.9)
Requires-Dist: sseclient (~=0.0)
Requires-Dist: six (~=1.11)
Requires-Dist: msgpack (~=0.5)
Requires-Dist: chardet (~=3.0)
Requires-Dist: wcwidth (>=0.1.7)
Requires-Dist: Pygments (>=2.2.0)
Requires-Dist: ml-crypto[pycryptodomex] (>=0.7.811)
Requires-Dist: missinglink-sdk (>=19.9.26893)
Requires-Dist: ml-legit (>=19.9.8734)
Requires-Dist: ml-core (>=19.9.3999)
Requires-Dist: sentry-sdk[flask] (<0.12.0)
Requires-Dist: azure-graphrbac (==0.53.0)
Requires-Dist: azure-mgmt-authorization (==0.51.1)
Requires-Dist: azure-mgmt-storage (~=3.1.0)
Requires-Dist: azure-keyvault (==1.1.0)
Requires-Dist: azure-mgmt-keyvault (==1.1.0)
Requires-Dist: azure-mgmt-msi (==0.2.0)
Requires-Dist: azure-mgmt-containerregistry (==2.7.0)
Requires-Dist: azure-mgmt-resource (==2.2.0)
Requires-Dist: urllib3 (<1.25,>=1.21.1)
Requires-Dist: Jinja2 (>=2.10.1)
Requires-Dist: retrying (>=1.3.3)
Requires-Dist: google-cloud-kms (>=1.1.0)
Requires-Dist: netifaces (<=0.10.9,>=0.10.6) ; sys_platform == 'win32'
